{
  "name":"山陽新幹線",
  "color":"#0000FF",
  "station_list":[
    {"code":100217,"name":"新大阪"},
    {"code":100302,"name":"新神戸"},
    {"code":100303,"name":"西明石"},
    {"code":100304,"name":"姫路"},
    {"code":100305,"name":"相生(兵庫)"},
    {"code":100306,"name":"岡山"},
    {"code":100307,"name":"新倉敷"},
    {"code":100308,"name":"福山"},
    {"code":100309,"name":"新尾道"},
    {"code":100310,"name":"三原"},
    {"code":100311,"name":"東広島"},
    {"code":100312,"name":"広島"},
    {"code":100313,"name":"新岩国"},
    {"code":100314,"name":"徳山"},
    {"code":100315,"name":"新山口"},
    {"code":100316,"name":"厚狭"},
    {"code":100317,"name":"新下関"},
    {"code":100318,"name":"小倉(福岡)"},
    {"code":100319,"name":"博多"}
  ]
}