{
  "code":99333,
  "id":"532627",
  "name":"流鉄流山線",
  "name_kana":"りゅうてつながれやません",
  "station_size":6,
  "company_code":145,
  "symbol":"RN",
  "station_list":[
    {"code":1132011,"id":"6a8917","name":"馬橋","name_kana":"まばし","lat":35.811682,"lng":139.917305,"prefecture":12,"numbering":[{"index":"01"}],"lines":[11320,99333],"attr":"cool","postal_code":"271-0051","address":"松戸市馬橋","next":[9933302,1132010,9932920,1130519,9930909,1130520,1130518,9932922,9932919,9932921],"voronoi":{"lat":35.803462,"lng":139.9288,"delta_lat":[0,-1621,13275,3285,3253,-1741,-5717,-6235,-3545,-373],"delta_lng":[0,-6167,-25791,1082,6379,9992,20900,-1644,-3307,-377]},"impl":true},
    {"code":9933302,"id":"12a205","name":"幸谷","name_kana":"こうや","lat":35.826642,"lng":139.919912,"prefecture":12,"numbering":[{"index":"02"}],"lines":[99333],"attr":"eco","postal_code":"270-0034","address":"松戸市新松戸１-４４１","next":[1130518,1132011,9933303,1130519,1132013],"voronoi":{"lat":35.819914,"lng":139.914295,"delta_lat":[0,1741,6643,4772,-2351],"delta_lng":[0,-9992,4716,14780,1403]},"impl":true},
    {"code":9933303,"id":"c15ee7","name":"小金城趾","name_kana":"こがねじょうし","lat":35.83601,"lng":139.916887,"prefecture":12,"numbering":[{"index":"03"}],"lines":[99333],"attr":"eco","postal_code":"270-0006","address":"松戸市大金平４-２１２-２","next":[9933304,9933302,1130518,9930911,1132013],"voronoi":{"lat":35.83307,"lng":139.9238,"delta_lat":[0,-4772,5328,12022,539],"delta_lng":[0,-14780,828,10296,5998]},"impl":true},
    {"code":9933304,"id":"00d840","name":"鰭ヶ崎","name_kana":"ひれがさき","lat":35.840948,"lng":139.911121,"prefecture":12,"numbering":[{"index":"04"}],"lines":[99333],"attr":"heat","postal_code":"270-0161","address":"千葉県流山市大字鰭ケ崎字宮ノ後1438番地3","next":[9933305,9933303,1130518,9930911],"voronoi":{"lat":35.833626,"lng":139.909848,"delta_lat":[0,11574,3783,-3335],"delta_lng":[0,-4646,3884,11058]},"impl":true},
    {"code":9933305,"id":"c8ca09","name":"平和台(千葉)","original_name":"平和台","name_kana":"へいわだい","lat":35.85123,"lng":139.901108,"prefecture":12,"numbering":[{"index":"05"}],"lines":[99333],"attr":"heat","postal_code":"270-0164","address":"流山市流山４-４８３","next":[1130517,9933304,1130518,9933306,9930911],"voronoi":{"lat":35.852513,"lng":139.908255,"delta_lat":[0,2529,-11809,1967,3783],"delta_lng":[0,-17449,4979,9417,3884]},"impl":true},
    {"code":9933306,"id":"42de63","name":"流山","name_kana":"ながれやま","lat":35.855771,"lng":139.901766,"prefecture":12,"numbering":[{"index":"06"}],"lines":[99333],"attr":"cool","postal_code":"270-0164","address":"流山市流山１-２６４","next":[2100421,2100420,1130517,9933305,1130516,9930911],"voronoi":{"lat":35.852513,"lng":139.908255,"delta_lat":[0,2529,6917,18460,-1204,-9440],"delta_lng":[0,-17449,-4829,1649,5763,16430]},"impl":true}
  ],
  "north":35.85638,
  "south":35.81176,
  "east":139.92033,
  "west":139.90118,
  "polyline_list":[
    {
      "start":"馬橋",
      "end":"流山",
      "lat":35.81176,
      "lng":139.91694,
      "delta_lat":[0,67,117,74,80,157,206,224,29,182,59,99,74,124,73,127,23,92,18,141,230,13,62,69,62,49,28,94,4,8,10,6,50,44,90,112,47,14,40,5,136,76,102,28,25,142,57,114,35,28,54,23,54,26,66,29,140,60,148,116],
      "delta_lng":[0,18,39,20,20,27,36,40,6,35,11,21,13,19,13,19,2,-13,-3,-36,-75,-5,-34,-66,-82,-63,-35,-120,-4,-11,-12,-8,-62,-54,-97,-115,-53,-15,-46,-5,-157,-91,-127,-35,-30,-173,-70,-138,-32,-20,-22,-5,-1,1,7,5,18,6,21,14]
    }
  ],
  "impl":true
}