{
  "code":99354,
  "id":"27ad42",
  "name":"東野鉄道",
  "name_kana":"とうやてつどう",
  "name_formal":"東野鉄道",
  "station_size":8,
  "closed":true,
  "station_list":[
    {"code":1131931,"id":"461bb5","name":"西那須野","original_name":"西那須野","name_kana":"にしなすの","closed":false,"lat":36.883726,"lng":139.986383,"prefecture":9,"lines":[11319,99354],"attr":"eco","postal_code":"329-2727","address":"那須塩原市永田町","next":[9935403,100406,9935402,1131930,9934107],"voronoi":{"type":"Feature","geometry":{"type":"Polygon","coordinates":[[[139.855718,36.946996],[139.992231,36.849293],[139.994653,36.856832],[139.990047,36.917439],[139.880217,36.995572],[139.855718,36.946996]]]},"properties":{}},"impl":true},
    {"code":9935402,"id":"a7f561","name":"乃木神社前","original_name":"乃木神社前","name_kana":"のぎじんじゃまえ","closed":true,"lat":36.884667,"lng":139.998764,"prefecture":9,"lines":[99354],"postal_code":"329-2704","address":"栃木県那須塩原市新南６９３−５","open_date":"1935-08-21","closed_date":"1968-12-16","next":[9935403,100406,1131931],"voronoi":{"type":"Feature","geometry":{"type":"Polygon","coordinates":[[[140.021753,36.902735],[139.990047,36.917439],[139.994653,36.856832],[140.021753,36.902735]]]},"properties":{}},"impl":false},
    {"code":9935403,"id":"db33c4","name":"大高前","original_name":"大高前","name_kana":"だいこうまえ","closed":true,"lat":36.873878,"lng":140.017039,"prefecture":9,"lines":[99354],"postal_code":"324-0058","address":"栃木県大田原市紫塚１丁目１","open_date":"1933-08-17","closed_date":"1968-12-16","next":[1131931,9935402,9935405,1131930,9935404,100406],"voronoi":{"type":"Feature","geometry":{"type":"Polygon","coordinates":[[[140.029013,36.896192],[140.006512,36.821217],[139.992231,36.849293],[139.994653,36.856832],[140.021753,36.902735],[140.028705,36.902298],[140.029013,36.896192]]]},"properties":{}},"impl":false},
    {"code":9935404,"id":"8b2c00","name":"大田原","original_name":"大田原","name_kana":"おおたわら","closed":true,"lat":36.870972,"lng":140.026722,"prefecture":9,"lines":[99354],"postal_code":"324-0051","address":"栃木県大田原市山の手２丁目１５","open_date":"1918-04-17","closed_date":"1968-12-16","next":[1131930,9935406,9935405,9935403,1131928],"voronoi":{"type":"Feature","geometry":{"type":"Polygon","coordinates":[[[140.049917,36.814785],[140.029013,36.896192],[140.006512,36.821217],[140.01883,36.790041],[140.04777,36.76989],[140.049917,36.814785]]]},"properties":{}},"impl":false},
    {"code":9935405,"id":"7c4fa5","name":"中田原","original_name":"中田原","name_kana":"なかたわら","closed":true,"lat":36.875196,"lng":140.043172,"prefecture":9,"lines":[99354],"postal_code":"324-0062","address":"栃木県大田原市中田原１５２５−７","open_date":"1933-08-17","closed_date":"1968-12-16","next":[9935403,9935406,9935404,100406],"voronoi":{"type":"Feature","geometry":{"type":"Polygon","coordinates":[[[140.028705,36.902298],[140.029013,36.896192],[140.049917,36.814785],[140.069645,36.918511],[140.028705,36.902298]]]},"properties":{}},"impl":false},
    {"code":9935406,"id":"3c0247","name":"金丸原","original_name":"金丸原","name_kana":"かねまるはら","closed":true,"lat":36.868502,"lng":140.078368,"prefecture":9,"lines":[99354],"postal_code":"324-0011","address":"栃木県大田原市北金丸１５６３−４","open_date":"1918-04-17","closed_date":"1968-12-16","next":[9935404,1123101,9935408,1133404,9935405,1131928,9935407,100406],"voronoi":{"type":"Feature","geometry":{"type":"Polygon","coordinates":[[[140.086415,36.922377],[140.08053,36.78078],[140.077855,36.7658],[140.047878,36.769764],[140.04777,36.76989],[140.049917,36.814785],[140.069645,36.918511],[140.070834,36.919592],[140.086415,36.922377]]]},"properties":{}},"impl":false},
    {"code":9935407,"id":"c73060","name":"白旗城址前","original_name":"白旗城址前","name_kana":"しろはたじょうしまえ","closed":true,"lat":36.86802,"lng":140.089964,"prefecture":9,"lines":[99354],"postal_code":"324-0011","address":"栃木県大田原市北金丸","open_date":"1936-05-14","closed_date":"1968-12-16","next":[1123101,9935408,9935406],"voronoi":{"type":"Feature","geometry":{"type":"Polygon","coordinates":[[[140.117885,36.931549],[140.08053,36.78078],[140.086415,36.922377],[140.117885,36.931549]]]},"properties":{}},"impl":false},
    {"code":9935408,"id":"52b914","name":"黒羽","original_name":"黒羽","name_kana":"くろばね","closed":true,"lat":36.862333,"lng":140.112917,"prefecture":9,"lines":[99354],"postal_code":"324-0241","address":"栃木県黒羽向町大田原市","open_date":"1918-04-17","closed_date":"1968-12-16","next":[1133832,1123104,9935407,1133405,9935406,1123102,1133408,1123103,1133826,1133825,1123101,1133404,1133827],"voronoi":{"type":"Feature","geometry":{"type":"Polygon","coordinates":[[[140.256427,36.908462],[140.247115,36.856021],[140.214934,36.772497],[140.135484,36.756691],[140.09655,36.759952],[140.077855,36.7658],[140.08053,36.78078],[140.117885,36.931549],[140.122192,36.933655],[140.159638,36.940788],[140.228911,36.93791],[140.252667,36.932713],[140.257104,36.923694],[140.256427,36.908462]]]},"properties":{}},"impl":false}
  ],
  "closed_date":"1968-12-16",
  "impl":false
}