{
  "station": "新多治見",
  "lat": 35.333639,
  "lng": 137.120056,
  "plus_code": {
    "compound_code": "84MC+F2 日本、岐阜県多治見市",
    "global_code": "8Q7V84MC+F2"
  },
  "results": [
    {
      "address_components": [
        {
          "long_name": "５",
          "short_name": "５",
          "types": [
            "premise"
          ]
        },
        {
          "long_name": "１丁目",
          "short_name": "１丁目",
          "types": [
            "political",
            "sublocality",
            "sublocality_level_3"
          ]
        },
        {
          "long_name": "田代町",
          "short_name": "田代町",
          "types": [
            "political",
            "sublocality",
            "sublocality_level_2"
          ]
        },
        {
          "long_name": "多治見市",
          "short_name": "多治見市",
          "types": [
            "locality",
            "political"
          ]
        },
        {
          "long_name": "岐阜県",
          "short_name": "岐阜県",
          "types": [
            "administrative_area_level_1",
            "political"
          ]
        },
        {
          "long_name": "日本",
          "short_name": "JP",
          "types": [
            "country",
            "political"
          ]
        },
        {
          "long_name": "507-0036",
          "short_name": "507-0036",
          "types": [
            "postal_code"
          ]
        }
      ],
      "formatted_address": "日本、〒507-0036 岐阜県多治見市田代町１丁目５",
      "geometry": {
        "bounds": {
          "northeast": {
            "lat": 35.3336826,
            "lng": 137.1199565
          },
          "southwest": {
            "lat": 35.3335958,
            "lng": 137.1198823
          }
        },
        "location": {
          "lat": 35.3336383,
          "lng": 137.1199111
        },
        "location_type": "ROOFTOP",
        "viewport": {
          "northeast": {
            "lat": 35.3349881802915,
            "lng": 137.1212683802915
          },
          "southwest": {
            "lat": 35.3322902197085,
            "lng": 137.1185704197085
          }
        }
      },
      "place_id": "ChIJj0NT6GZqA2AR0sGjBq4OLtA",
      "types": [
        "premise"
      ]
    },
    {
      "address_components": [
        {
          "long_name": "４−２",
          "short_name": "４−２",
          "types": [
            "premise"
          ]
        },
        {
          "long_name": "１丁目",
          "short_name": "１丁目",
          "types": [
            "political",
            "sublocality",
            "sublocality_level_3"
          ]
        },
        {
          "long_name": "田代町",
          "short_name": "田代町",
          "types": [
            "political",
            "sublocality",
            "sublocality_level_2"
          ]
        },
        {
          "long_name": "多治見市",
          "short_name": "多治見市",
          "types": [
            "locality",
            "political"
          ]
        },
        {
          "long_name": "岐阜県",
          "short_name": "岐阜県",
          "types": [
            "administrative_area_level_1",
            "political"
          ]
        },
        {
          "long_name": "日本",
          "short_name": "JP",
          "types": [
            "country",
            "political"
          ]
        },
        {
          "long_name": "507-0036",
          "short_name": "507-0036",
          "types": [
            "postal_code"
          ]
        }
      ],
      "formatted_address": "日本、〒507-0036 岐阜県多治見市田代町１丁目４−２",
      "geometry": {
        "location": {
          "lat": 35.3335418,
          "lng": 137.1202558
        },
        "location_type": "ROOFTOP",
        "viewport": {
          "northeast": {
            "lat": 35.3348907802915,
            "lng": 137.1216047802915
          },
          "southwest": {
            "lat": 35.3321928197085,
            "lng": 137.1189068197085
          }
        }
      },
      "place_id": "ChIJD4z67GZqA2ARemt0_j0J8xo",
      "plus_code": {
        "compound_code": "84MC+C4 日本、岐阜県多治見市",
        "global_code": "8Q7V84MC+C4"
      },
      "types": [
        "street_address"
      ]
    },
    {
      "address_components": [
        {
          "long_name": "６−１",
          "short_name": "６−１",
          "types": [
            "premise"
          ]
        },
        {
          "long_name": "１丁目",
          "short_name": "１丁目",
          "types": [
            "political",
            "sublocality",
            "sublocality_level_3"
          ]
        },
        {
          "long_name": "田代町",
          "short_name": "田代町",
          "types": [
            "political",
            "sublocality",
            "sublocality_level_2"
          ]
        },
        {
          "long_name": "多治見市",
          "short_name": "多治見市",
          "types": [
            "locality",
            "political"
          ]
        },
        {
          "long_name": "岐阜県",
          "short_name": "岐阜県",
          "types": [
            "administrative_area_level_1",
            "political"
          ]
        },
        {
          "long_name": "日本",
          "short_name": "JP",
          "types": [
            "country",
            "political"
          ]
        },
        {
          "long_name": "507-0036",
          "short_name": "507-0036",
          "types": [
            "postal_code"
          ]
        }
      ],
      "formatted_address": "日本、〒507-0036 岐阜県多治見市田代町１丁目６−１",
      "geometry": {
        "location": {
          "lat": 35.3334333,
          "lng": 137.1199862
        },
        "location_type": "ROOFTOP",
        "viewport": {
          "northeast": {
            "lat": 35.33478228029149,
            "lng": 137.1213351802915
          },
          "southwest": {
            "lat": 35.3320843197085,
            "lng": 137.1186372197085
          }
        }
      },
      "place_id": "ChIJZeXp7mZqA2ARd2C-Do67TJU",
      "plus_code": {
        "compound_code": "84M9+9X 日本、岐阜県多治見市",
        "global_code": "8Q7V84M9+9X"
      },
      "types": [
        "establishment",
        "point_of_interest",
        "school"
      ]
    },
    {
      "address_components": [
        {
          "long_name": "Unnamed Road",
          "short_name": "Unnamed Road",
          "types": [
            "route"
          ]
        },
        {
          "long_name": "１丁目",
          "short_name": "１丁目",
          "types": [
            "political",
            "sublocality",
            "sublocality_level_3"
          ]
        },
        {
          "long_name": "田代町",
          "short_name": "田代町",
          "types": [
            "political",
            "sublocality",
            "sublocality_level_2"
          ]
        },
        {
          "long_name": "多治見市",
          "short_name": "多治見市",
          "types": [
            "locality",
            "political"
          ]
        },
        {
          "long_name": "岐阜県",
          "short_name": "岐阜県",
          "types": [
            "administrative_area_level_1",
            "political"
          ]
        },
        {
          "long_name": "日本",
          "short_name": "JP",
          "types": [
            "country",
            "political"
          ]
        },
        {
          "long_name": "507-0036",
          "short_name": "507-0036",
          "types": [
            "postal_code"
          ]
        }
      ],
      "formatted_address": "Unnamed Road, １丁目 田代町 多治見市 岐阜県 507-0036 日本",
      "geometry": {
        "bounds": {
          "northeast": {
            "lat": 35.3337358,
            "lng": 137.1201937
          },
          "southwest": {
            "lat": 35.3332163,
            "lng": 137.1199258
          }
        },
        "location": {
          "lat": 35.3335434,
          "lng": 137.1201839
        },
        "location_type": "GEOMETRIC_CENTER",
        "viewport": {
          "northeast": {
            "lat": 35.3348250302915,
            "lng": 137.1214087302915
          },
          "southwest": {
            "lat": 35.3321270697085,
            "lng": 137.1187107697085
          }
        }
      },
      "place_id": "ChIJ2wUm7GZqA2ARxg_tdvhgKzY",
      "types": [
        "route"
      ]
    },
    {
      "address_components": [
        {
          "long_name": "１丁目",
          "short_name": "１丁目",
          "types": [
            "political",
            "sublocality",
            "sublocality_level_3"
          ]
        },
        {
          "long_name": "田代町",
          "short_name": "田代町",
          "types": [
            "political",
            "sublocality",
            "sublocality_level_2"
          ]
        },
        {
          "long_name": "多治見市",
          "short_name": "多治見市",
          "types": [
            "locality",
            "political"
          ]
        },
        {
          "long_name": "岐阜県",
          "short_name": "岐阜県",
          "types": [
            "administrative_area_level_1",
            "political"
          ]
        },
        {
          "long_name": "日本",
          "short_name": "JP",
          "types": [
            "country",
            "political"
          ]
        },
        {
          "long_name": "507-0036",
          "short_name": "507-0036",
          "types": [
            "postal_code"
          ]
        }
      ],
      "formatted_address": "日本、〒507-0036 岐阜県多治見市田代町１丁目",
      "geometry": {
        "bounds": {
          "northeast": {
            "lat": 35.3342805,
            "lng": 137.1218113
          },
          "southwest": {
            "lat": 35.3319954,
            "lng": 137.1190736
          }
        },
        "location": {
          "lat": 35.33312840000001,
          "lng": 137.1197684
        },
        "location_type": "APPROXIMATE",
        "viewport": {
          "northeast": {
            "lat": 35.3344869302915,
            "lng": 137.1218113
          },
          "southwest": {
            "lat": 35.3317889697085,
            "lng": 137.1190736
          }
        }
      },
      "place_id": "ChIJiX9fi2ZqA2ARqtcG0vqz4PE",
      "types": [
        "political",
        "sublocality",
        "sublocality_level_3"
      ]
    },
    {
      "address_components": [
        {
          "long_name": "507-0036",
          "short_name": "507-0036",
          "types": [
            "postal_code"
          ]
        },
        {
          "long_name": "田代町",
          "short_name": "田代町",
          "types": [
            "political",
            "sublocality",
            "sublocality_level_2"
          ]
        },
        {
          "long_name": "多治見市",
          "short_name": "多治見市",
          "types": [
            "locality",
            "political"
          ]
        },
        {
          "long_name": "岐阜県",
          "short_name": "岐阜県",
          "types": [
            "administrative_area_level_1",
            "political"
          ]
        },
        {
          "long_name": "日本",
          "short_name": "JP",
          "types": [
            "country",
            "political"
          ]
        }
      ],
      "formatted_address": "日本 〒507-0036",
      "geometry": {
        "bounds": {
          "northeast": {
            "lat": 35.3342805,
            "lng": 137.1218113
          },
          "southwest": {
            "lat": 35.3312624,
            "lng": 137.1154544
          }
        },
        "location": {
          "lat": 35.3325948,
          "lng": 137.1185505
        },
        "location_type": "APPROXIMATE",
        "viewport": {
          "northeast": {
            "lat": 35.3342805,
            "lng": 137.1218113
          },
          "southwest": {
            "lat": 35.3312624,
            "lng": 137.1154544
          }
        }
      },
      "place_id": "ChIJ3SPE8WZqA2ARymttgNze9Gw",
      "types": [
        "postal_code"
      ]
    },
    {
      "address_components": [
        {
          "long_name": "田代町",
          "short_name": "田代町",
          "types": [
            "political",
            "sublocality",
            "sublocality_level_2"
          ]
        },
        {
          "long_name": "多治見市",
          "short_name": "多治見市",
          "types": [
            "locality",
            "political"
          ]
        },
        {
          "long_name": "岐阜県",
          "short_name": "岐阜県",
          "types": [
            "administrative_area_level_1",
            "political"
          ]
        },
        {
          "long_name": "日本",
          "short_name": "JP",
          "types": [
            "country",
            "political"
          ]
        },
        {
          "long_name": "507-0036",
          "short_name": "507-0036",
          "types": [
            "postal_code"
          ]
        }
      ],
      "formatted_address": "日本、〒507-0036 岐阜県多治見市田代町",
      "geometry": {
        "bounds": {
          "northeast": {
            "lat": 35.3342805,
            "lng": 137.1218113
          },
          "southwest": {
            "lat": 35.3312624,
            "lng": 137.1154544
          }
        },
        "location": {
          "lat": 35.3325948,
          "lng": 137.1185505
        },
        "location_type": "APPROXIMATE",
        "viewport": {
          "northeast": {
            "lat": 35.3342805,
            "lng": 137.1218113
          },
          "southwest": {
            "lat": 35.3312624,
            "lng": 137.1154544
          }
        }
      },
      "place_id": "ChIJqeNfGmdqA2AR9lYKyK7Qt9M",
      "types": [
        "political",
        "sublocality",
        "sublocality_level_2"
      ]
    },
    {
      "address_components": [
        {
          "long_name": "多治見市",
          "short_name": "多治見市",
          "types": [
            "locality",
            "political"
          ]
        },
        {
          "long_name": "岐阜県",
          "short_name": "岐阜県",
          "types": [
            "administrative_area_level_1",
            "political"
          ]
        },
        {
          "long_name": "日本",
          "short_name": "JP",
          "types": [
            "country",
            "political"
          ]
        }
      ],
      "formatted_address": "日本、岐阜県多治見市",
      "geometry": {
        "bounds": {
          "northeast": {
            "lat": 35.4030491,
            "lng": 137.1864006
          },
          "southwest": {
            "lat": 35.2703422,
            "lng": 137.0459087
          }
        },
        "location": {
          "lat": 35.3327697,
          "lng": 137.1321388
        },
        "location_type": "APPROXIMATE",
        "viewport": {
          "northeast": {
            "lat": 35.4030491,
            "lng": 137.1864006
          },
          "southwest": {
            "lat": 35.2703422,
            "lng": 137.0459087
          }
        }
      },
      "place_id": "ChIJrQ2X519qA2ARJlle7zz6MQk",
      "types": [
        "locality",
        "political"
      ]
    },
    {
      "address_components": [
        {
          "long_name": "岐阜県",
          "short_name": "岐阜県",
          "types": [
            "administrative_area_level_1",
            "political"
          ]
        },
        {
          "long_name": "日本",
          "short_name": "JP",
          "types": [
            "country",
            "political"
          ]
        }
      ],
      "formatted_address": "日本、岐阜県",
      "geometry": {
        "bounds": {
          "northeast": {
            "lat": 36.465098,
            "lng": 137.6532657
          },
          "southwest": {
            "lat": 35.1337282,
            "lng": 136.2762022
          }
        },
        "location": {
          "lat": 35.7437491,
          "lng": 136.9805103
        },
        "location_type": "APPROXIMATE",
        "viewport": {
          "northeast": {
            "lat": 36.465098,
            "lng": 137.6532657
          },
          "southwest": {
            "lat": 35.1337282,
            "lng": 136.2762022
          }
        }
      },
      "place_id": "ChIJi8OICvLxAmARZ9bM7q0UJ68",
      "types": [
        "administrative_area_level_1",
        "political"
      ]
    },
    {
      "address_components": [
        {
          "long_name": "日本",
          "short_name": "JP",
          "types": [
            "country",
            "political"
          ]
        }
      ],
      "formatted_address": "日本",
      "geometry": {
        "bounds": {
          "northeast": {
            "lat": 45.6412626,
            "lng": 154.0031455
          },
          "southwest": {
            "lat": 20.3585295,
            "lng": 122.8554688
          }
        },
        "location": {
          "lat": 36.204824,
          "lng": 138.252924
        },
        "location_type": "APPROXIMATE",
        "viewport": {
          "northeast": {
            "lat": 45.6412626,
            "lng": 154.0031455
          },
          "southwest": {
            "lat": 20.3585295,
            "lng": 122.8554688
          }
        }
      },
      "place_id": "ChIJLxl_1w9OZzQRRFJmfNR1QvU",
      "types": [
        "country",
        "political"
      ]
    },
    {
      "address_components": [
        {
          "long_name": "84MC+F2",
          "short_name": "84MC+F2",
          "types": [
            "plus_code"
          ]
        },
        {
          "long_name": "多治見市",
          "short_name": "多治見市",
          "types": [
            "locality",
            "political"
          ]
        },
        {
          "long_name": "岐阜県",
          "short_name": "岐阜県",
          "types": [
            "administrative_area_level_1",
            "political"
          ]
        },
        {
          "long_name": "日本",
          "short_name": "JP",
          "types": [
            "country",
            "political"
          ]
        }
      ],
      "formatted_address": "84MC+F2 日本、岐阜県多治見市",
      "geometry": {
        "bounds": {
          "northeast": {
            "lat": 35.33374999999999,
            "lng": 137.120125
          },
          "southwest": {
            "lat": 35.333625,
            "lng": 137.12
          }
        },
        "location": {
          "lat": 35.333639,
          "lng": 137.120056
        },
        "location_type": "ROOFTOP",
        "viewport": {
          "northeast": {
            "lat": 35.3350364802915,
            "lng": 137.1214114802915
          },
          "southwest": {
            "lat": 35.3323385197085,
            "lng": 137.1187135197085
          }
        }
      },
      "place_id": "GhIJx9XIrrSqQUARCTauf9cjYUA",
      "plus_code": {
        "compound_code": "84MC+F2 日本、岐阜県多治見市",
        "global_code": "8Q7V84MC+F2"
      },
      "types": [
        "plus_code"
      ]
    }
  ]
}